hros/__init__.py
hros/__main__.py
hros-0.4.dist-info/LICENSE
hros-0.4.dist-info/METADATA
hros-0.4.dist-info/WHEEL
hros-0.4.dist-info/entry_points.txt
hros-0.4.dist-info/top_level.txt
hros-0.4.dist-info/RECORD
